linkmotion/__init__.py
linkmotion/py.typed
linkmotion/collision/__init__.py
linkmotion/collision/manager.py
linkmotion/const/__init__.py
linkmotion/const/const.py
linkmotion/modeling/__init__.py
linkmotion/modeling/remove.py
linkmotion/modeling/sweep.py
linkmotion/move/__init__.py
linkmotion/move/manager.py
linkmotion/range/__init__.py
linkmotion/range/limit.py
linkmotion/range/manager.py
linkmotion/range/range_cal.py
linkmotion/range/range_read.py
linkmotion/robot/__init__.py
linkmotion/robot/custom.py
linkmotion/robot/joint.py
linkmotion/robot/link.py
linkmotion/robot/robot.py
linkmotion/robot/shape/__init__.py
linkmotion/robot/shape/base.py
linkmotion/robot/shape/box.py
linkmotion/robot/shape/capsule.py
linkmotion/robot/shape/cone.py
linkmotion/robot/shape/convex.py
linkmotion/robot/shape/cylinder.py
linkmotion/robot/shape/mesh.py
linkmotion/robot/shape/sphere.py
linkmotion/transform/__init__.py
linkmotion/transform/manager.py
linkmotion/transform/transform.py
linkmotion/typing/__init__.py
linkmotion/typing/numpy.py
linkmotion/urdf/__init__.py
linkmotion/urdf/parser.py
linkmotion/urdf/writer.py
linkmotion/visual/__init__.py
linkmotion/visual/base.py
linkmotion/visual/collision.py
linkmotion/visual/mesh.py
linkmotion/visual/move.py
linkmotion/visual/range.py
linkmotion/visual/robot.py
linkmotion-0.2.0.dist-info/METADATA
linkmotion-0.2.0.dist-info/WHEEL
linkmotion-0.2.0.dist-info/licenses/LICENSE
linkmotion-0.2.0.dist-info/RECORD
