Metadata-Version: 2.4
Name: linkmotion
Version: 0.2.0
Summary: LinkMotion is a comprehensive robotics library that provides tools for robot modeling, joint control, collision detection, visualization, and URDF import/export functionality.
Project-URL: Homepage, https://github.com/hshrg-kw/linkmotion
Project-URL: Documentation, https://hshrg-kw.github.io/linkmotion/
Project-URL: Repository, https://github.com/hshrg-kw/linkmotion
Project-URL: Issues, https://github.com/hshrg-kw/linkmotion/issues
Author-email: hshrg-kw <232059135+hshrg-kw@users.noreply.github.com>
Maintainer-email: hshrg-kw <232059135+hshrg-kw@users.noreply.github.com>
License-Expression: MIT
License-File: LICENSE
Keywords: automation,collision detection,kinematics,robotics,simulation,urdf,visualization
Classifier: Development Status :: 4 - Beta
Classifier: Intended Audience :: Developers
Classifier: Programming Language :: Python :: 3
Classifier: Programming Language :: Python :: 3.12
Classifier: Programming Language :: Python :: 3.13
Requires-Python: >=3.12
Requires-Dist: manifold3d>=3.2.1
Requires-Dist: psutil>=7.1.0
Requires-Dist: python-fcl>=0.7.0.8
Requires-Dist: scipy>=1.16.2
Requires-Dist: shapely>=2.1.2
Requires-Dist: tqdm>=4.67.1
Requires-Dist: trimesh>=4.8.2
Requires-Dist: wurlitzer>=3.1.1
Provides-Extra: jup
Requires-Dist: jupyter>=1.1.1; extra == 'jup'
Requires-Dist: k3d>=2.17.0; extra == 'jup'
Requires-Dist: plotly>=6.3.0; extra == 'jup'
